d6tcollect/__init__.py
d6tcollect-1.0.6.dist-info/LICENSE
d6tcollect-1.0.6.dist-info/METADATA
d6tcollect-1.0.6.dist-info/WHEEL
d6tcollect-1.0.6.dist-info/top_level.txt
d6tcollect-1.0.6.dist-info/RECORD
