Metadata-Version: 2.1
Name: d6tcollect
Version: 1.0.6
Summary: d6tcollect: collects anonymous usage statistics for python libraries
Home-page: https://github.com/d6t/d6tcollect
Author: DataBolt Team
Author-email: support@databolt.tech
License: MIT
Keywords: d6tcollect,usage tracking,engagement tracking
Platform: UNKNOWN
Requires-Python: >=3.5
Provides-Extra: track
Requires-Dist: beautifulsoup4 ; extra == 'track'
